quantdata_sdk/__init__.py
quantdata_sdk/__version__.py
quantdata_sdk/api.py
quantdata_sdk/constants.py
quantdata_sdk/entry_points.py
quantdata_sdk/response.py
quantdata_sdk/utils.py
quantumdata_sdk-0.2.0.dist-info/LICENSE
quantumdata_sdk-0.2.0.dist-info/METADATA
quantumdata_sdk-0.2.0.dist-info/WHEEL
quantumdata_sdk-0.2.0.dist-info/entry_points.txt
quantumdata_sdk-0.2.0.dist-info/top_level.txt
quantumdata_sdk-0.2.0.dist-info/RECORD
